coffeetests/__init__.py
coffeetests/hello.py
coffeetests-0.1.0.dist-info/METADATA
coffeetests-0.1.0.dist-info/WHEEL
coffeetests-0.1.0.dist-info/RECORD
