Metadata-Version: 2.1
Name: coffeetests
Version: 0.1.0
Summary: Testing things
Author-email: Jacob Coffee <jacob@z7x.org>
License: MIT
Requires-Python: >=3.12
